leotune/__init__.py
leotune/__main__.py
leotune/cli.py
leotune/lrc.py
leotune/data/__init__.py
leotune/data/acgnjrock.py
leotune/data/leoneed.py
leotune/data/others.py
leotune-0.0.4.dist-info/LICENSE
leotune-0.0.4.dist-info/METADATA
leotune-0.0.4.dist-info/WHEEL
leotune-0.0.4.dist-info/entry_points.txt
leotune-0.0.4.dist-info/top_level.txt
leotune-0.0.4.dist-info/RECORD
