Metadata-Version: 2.1
Name: leotune
Version: 0.0.4
Summary: A Simple Python-based CLI-tool throwing out lyrics of VOCALOID works, which is similar to "fortune"
Home-page: https://github.com/sandyzikun/leotune.git
Classifier: Programming Language :: Python :: 3
Classifier: License :: OSI Approved :: GNU General Public License v3 (GPLv3)
License-File: LICENSE
